setup.cfg
setup.py
canfar/__canfarcloud_version__.py
canfar/__init__.py
canfar/proc/__init__.py
canfar/proc/client.py
canfarcloud.egg-info/PKG-INFO
canfarcloud.egg-info/SOURCES.txt
canfarcloud.egg-info/dependency_links.txt
canfarcloud.egg-info/namespace_packages.txt
canfarcloud.egg-info/not-zip-safe
canfarcloud.egg-info/pbr.json
canfarcloud.egg-info/requires.txt
canfarcloud.egg-info/top_level.txt
scripts/canfar-submit-job