Metadata-Version: 1.1
Name: canfarcloud
Version: 0.2.4
Summary: Python client libraries and scripts for CANFAR OpenStack cloud services
Home-page: https://github.com/canfar/python-canfar-clients
Author: Ed Chapin, Jeff Burke, Dustin Jenkins
Author-email: cadc@nrc.ca
License: GNU Affero General Public License v3.0
Platform: UNKNOWN
Provides: canfarcloud
